kuorma/__init__.py
kuorma/kuorma.py
kuorma/testaa.py
python_kuorma-0.1.dist-info/METADATA
python_kuorma-0.1.dist-info/WHEEL
python_kuorma-0.1.dist-info/historia.json
python_kuorma-0.1.dist-info/top_level.txt
python_kuorma-0.1.dist-info/RECORD
