Metadata-Version: 2.1
Name: python-kuorma
Version: 0.1
Summary: Python-funktioiden ja -metodien ajonaikainen ylikuormitus
Home-page: https://github.com/an7oine/python-kuorma.git
Author: Antti Hautaniemi
Author-email: antti.hautaniemi@pispalanit.fi
License: UNKNOWN
Platform: UNKNOWN
